odoo/addons/report_qweb_element_page_visibility/README.rst
odoo/addons/report_qweb_element_page_visibility/__init__.py
odoo/addons/report_qweb_element_page_visibility/__manifest__.py
odoo/addons/report_qweb_element_page_visibility/i18n/it.po
odoo/addons/report_qweb_element_page_visibility/i18n/report_qweb_element_page_visibility.pot
odoo/addons/report_qweb_element_page_visibility/readme/CONTRIBUTORS.rst
odoo/addons/report_qweb_element_page_visibility/readme/DESCRIPTION.rst
odoo/addons/report_qweb_element_page_visibility/readme/USAGE.rst
odoo/addons/report_qweb_element_page_visibility/static/description/icon.png
odoo/addons/report_qweb_element_page_visibility/static/description/index.html
odoo/addons/report_qweb_element_page_visibility/views/layouts.xml
odoo13_addon_report_qweb_element_page_visibility-13.0.1.1.0.dist-info/METADATA
odoo13_addon_report_qweb_element_page_visibility-13.0.1.1.0.dist-info/WHEEL
odoo13_addon_report_qweb_element_page_visibility-13.0.1.1.0.dist-info/top_level.txt
odoo13_addon_report_qweb_element_page_visibility-13.0.1.1.0.dist-info/RECORD
